LICENSE
LICENSE.md
README.md
export.py
setup.cfg
setup.py
import_export.egg-info/PKG-INFO
import_export.egg-info/SOURCES.txt
import_export.egg-info/dependency_links.txt
import_export.egg-info/top_level.txt