Metadata-Version: 2.1
Name: import-export
Version: 0.3.0
Summary: A Python module methods decorator
Home-page: https://github.com/ablaternae/py-export
Author: JL Connor
Author-email: AbLaternae@outlook.com
License: GLWTPL
Keywords: python,import,module,package,export
Platform: any
Classifier: Development Status :: 4 - Beta
Classifier: Intended Audience :: Developers
Classifier: License :: Freeware
Classifier: License :: OSI Approved :: BSD License
Classifier: Operating System :: OS Independent
Classifier: Programming Language :: Python
Classifier: Programming Language :: Python :: 2
Classifier: Programming Language :: Python :: 3
Classifier: Topic :: Software Development :: Libraries :: Python Modules
Classifier: Topic :: Utilities
License-File: LICENSE
License-File: LICENSE.md
